{
 "acquisition": {
  "mount": "fixed",
  "exif": {
   "camera": "NIKON Z6_3",
   "lens": "NIKKOR Z 24-70mm f/4 S",
   "focal_length_mm": 70.0,
   "exposure_s": 6.0,
   "iso": 1600,
   "image_wh": [
    6064,
    4040
   ],
   "fov_deg": 28.6,
   "pixel_scale_arcsec": 16.979,
   "cadence_s": 2852.69,
   "frames": 4,
   "time_span_s": 12505.4
  }
 },
 "capture_runs": [
  {
   "run": 1,
   "first": "DSC_6679.NEF",
   "last": "DSC_6679.NEF",
   "n": 1
  },
  {
   "run": 2,
   "first": "DSC_6680.NEF",
   "last": "DSC_6680.NEF",
   "n": 1
  },
  {
   "run": 3,
   "first": "DSC_7940.NEF",
   "last": "DSC_7940.NEF",
   "n": 1
  },
  {
   "run": 4,
   "first": "DSC_8340.NEF",
   "last": "DSC_8340.NEF",
   "n": 1
  }
 ],
 "frames": [
  {
   "file": "DSC_6679.NEF",
   "n_trails": 3,
   "stellar_trail_px": 1.8,
   "counts": {
    "satellite": 1
   },
   "objects": [
    {
     "cls": "satellite",
     "confidence": 0.7,
     "reason": "3 colinear fragments of one trail, span 364px",
     "evidence": {
      "span_px": 364,
      "n_fragments": 3,
      "pa_deg": 86.7
     },
     "streaks": [
      {
       "length": 131.18525047420604,
       "width": 0.8695920060520196,
       "sagitta": 2.571431785854075,
       "elong": 86.48756102226412,
       "curvature": 0.01960153124348134,
       "bright_cv": 0.21782396733760834,
       "pa_deg": 86.65488625690904,
       "cx": 2024.0100143790144,
       "cy": 788.7490393842288,
       "npix": 157
      },
      {
       "length": 48.03709691156882,
       "width": 0.5732761585633566,
       "sagitta": 0.7006604718685254,
       "elong": 48.51492706920061,
       "curvature": 0.014585820478668117,
       "bright_cv": 0.11255969107151031,
       "pa_deg": 86.82534429550766,
       "cx": 2029.9536294890909,
       "cy": 885.7462877628917,
       "npix": 54
      },
      {
       "length": 145.27794817638525,
       "width": 0.6320311506919598,
       "sagitta": 1.0323475919814902,
       "elong": 130.57311107049574,
       "curvature": 0.0071060171549786316,
       "bright_cv": 0.1251082420349121,
       "pa_deg": 86.2259460466348,
       "cx": 2038.254324966099,
       "cy": 1014.5573899469745,
       "npix": 167
      }
     ]
    }
   ]
  },
  {
   "file": "DSC_6680.NEF",
   "n_trails": 0,
   "stellar_trail_px": 1.8,
   "counts": {},
   "objects": []
  },
  {
   "file": "DSC_7940.NEF",
   "n_trails": 0,
   "stellar_trail_px": 1.8,
   "counts": {},
   "objects": []
  },
  {
   "file": "DSC_8340.NEF",
   "n_trails": 0,
   "stellar_trail_px": 1.9,
   "counts": {},
   "objects": []
  }
 ],
 "unique_objects": [
  {
   "cls": "satellite",
   "files": [
    "DSC_6679.NEF"
   ],
   "first": "DSC_6679.NEF",
   "last": "DSC_6679.NEF",
   "n": 1,
   "pa": 86.7
  }
 ]
}