{
 "_readme": "Measured no-regression record \u2014 written by sweep.py --rebaseline, never by hand.",
 "dataset": "session_02/set-02",
 "approved": null,
 "stack": "results/stack_set-02_spcc.fit",
 "stack_sha256": "77115d49f5c8ef89fa669a73b2ad3a3287cff31a0ca705a87e5e157ad8849e33",
 "rebuild": "python3 scripts/render/starcomb.py session_02 set-02 --stack session_02/results/stack_set-02_spcc.fit --lossless",
 "metrics": {
  "qa_starless.color": 2.0,
  "qa_starless.grad": 2.9923755810629746,
  "qa_starless.resid": 1.000476458218697,
  "qa_starless.ring_l": 6.555555555555558,
  "qa_starless.floor": 10.5,
  "star_shells.aura_lum": 10.0,
  "star_shells.shell_chroma": 20.015100479125977
 },
 "gate_pass": true,
 "artifact_sha256": {
  "jpg": "e5fdd3158f58744bbdef66baaec60ac3b0def85132f67a497aec5588af6dc810",
  "png": "ff17f4b1e17a70258b0a7181d9378ccfca0a21702327a309be3bc90c8a8dbcab",
  "png16": "962f7b6401a65402e29cb833e607a1a4d0fe296b3ae4a2dfcf31daac4221a49a",
  "starless_jpg": "abb571c8ade6960d93ee102fe60849a3aa2689fd9dc4d5763b484e8dd234fea6",
  "starless_png": "1900c2a0e0d0f61f613736a3438e1ab43022d22f6337235a96b34d0c1f105480",
  "starless_png16": "358489918fb5e9ae0c2a4e1abf25fa6181ced8b2ee23b7ecf9e900899ba4a730"
 },
 "recipe": {
  "bgelin_mode": "gx",
  "starless_target": 0.07,
  "starless_denoise": "vstpost",
  "stretch_mode": "mtf",
  "ghs_sp_k": 2.0,
  "ghs_amount": 3.0,
  "ghs_focus": 3.0,
  "sep_prom": 6.0,
  "sep_engine": "auto",
  "chroma_core": 4.0,
  "lum_core": 2.0,
  "core_order": "pre",
  "stretch_linked": "linked",
  "perline_scale": 0.5,
  "ppgamma": 2.7,
  "ppsigma": 1.0,
  "satgamma": 1.1,
  "huerot_from": 120.0,
  "huerot_to": 147.5,
  "huerot_by": -35.0,
  "scnr": 0.5,
  "satu": 0.2,
  "cull_pct": 50.0,
  "stars_peak": 0.97,
  "stars_anchor": "catalog",
  "stars_floor": 3.0,
  "stars_opacity": 1.0,
  "black_point": 8.0,
  "jpg_quality": 100,
  "jpg_subsampling": 0,
  "noise_anchor_k": null
 },
 "date": "2026-07-12 13:29:17",
 "git": "3eca892"
}