{
 "_readme": "Measured no-regression record \u2014 written by sweep.py --rebaseline, never by hand.",
 "dataset": "siril-m8m20/lpro_180s",
 "approved": null,
 "stack": "results/stack_lpro_180s_spcc.fit",
 "stack_sha256": "f9a941a7e8f40c6b133839d684c7e5cf6814595460a814ee7e30a0671e0e9ffc",
 "rebuild": "python3 scripts/render/starcomb.py siril-m8m20 lpro_180s --stack siril-m8m20/results/stack_lpro_180s_spcc.fit --lossless",
 "metrics": {
  "qa_starless.color": 22.0,
  "qa_starless.grad": 1.9680066253356383,
  "qa_starless.resid": 2.184763718063637,
  "qa_starless.ring_l": 3.2222222222222214,
  "qa_starless.floor": 9.0,
  "star_shells.aura_lum": 2.25,
  "star_shells.shell_chroma": 15.196649551391602
 },
 "gate_pass": false,
 "artifact_sha256": {
  "jpg": "bb8876dd85114cd14ddb80f061203d2fd5538f79ddb40c825e0d7c69ef04d8b3",
  "png": "c444adb1c5069c652fffe2630b4522d6a178d50f04a2cd4dc1dae36022d24a93",
  "png16": "7909b0e27e35aa43be762eca26b831da7bac81c23ec1ae34180f386c01d9e745",
  "starless_jpg": "858b6ff7b85a4001f1df701d2907f97f833b86156120b5ae0f1757193d980b83",
  "starless_png": "288f38fd62b728236556826302a2b0d56313e49062b297b7d5ef0da455bad78f",
  "starless_png16": "7ed2625cc0845974f2f389608da55a66be4dfef4ed92a222f7265ad3fca689fa"
 },
 "recipe": {
  "bgelin_mode": "gx",
  "starless_target": 0.07,
  "starless_denoise": "vstpost",
  "stretch_mode": "mtf",
  "ghs_sp_k": 2.0,
  "ghs_amount": 3.0,
  "ghs_focus": 3.0,
  "sep_prom": 6.0,
  "sep_engine": "auto",
  "chroma_core": 4.0,
  "lum_core": 2.0,
  "core_order": "pre",
  "stretch_linked": "linked",
  "perline_scale": 0.5,
  "ppgamma": 2.7,
  "ppsigma": 1.0,
  "satgamma": 1.1,
  "huerot_from": 120.0,
  "huerot_to": 147.5,
  "huerot_by": -35.0,
  "scnr": 0.5,
  "satu": 0.2,
  "cull_pct": 50.0,
  "stars_peak": 0.97,
  "stars_anchor": "catalog",
  "stars_floor": 3.0,
  "stars_opacity": 1.0,
  "black_point": 8.0,
  "jpg_quality": 100,
  "jpg_subsampling": 0,
  "noise_anchor_k": null
 },
 "date": "2026-07-12 00:14:40",
 "git": "663a798",
 "color_scope_ack": true
}